flask_jsonrpc/__init__.py
flask_jsonrpc/app.py
flask_jsonrpc/blueprints.py
flask_jsonrpc/descriptor.py
flask_jsonrpc/encoders.py
flask_jsonrpc/exceptions.py
flask_jsonrpc/funcutils.py
flask_jsonrpc/globals.py
flask_jsonrpc/helpers.py
flask_jsonrpc/py.typed
flask_jsonrpc/site.py
flask_jsonrpc/typing.py
flask_jsonrpc/utils.py
flask_jsonrpc/views.py
flask_jsonrpc/wrappers.py
flask_jsonrpc/conf/__init__.py
flask_jsonrpc/conf/global_settings.py
flask_jsonrpc/contrib/__init__.py
flask_jsonrpc/contrib/browse/__init__.py
flask_jsonrpc/contrib/browse/static/.editorconfig
flask_jsonrpc/contrib/browse/static/android-chrome-192x192.png
flask_jsonrpc/contrib/browse/static/android-chrome-512x512.png
flask_jsonrpc/contrib/browse/static/apple-touch-icon.png
flask_jsonrpc/contrib/browse/static/favicon-16x16.png
flask_jsonrpc/contrib/browse/static/favicon-32x32.png
flask_jsonrpc/contrib/browse/static/favicon.ico
flask_jsonrpc/contrib/browse/static/robots.txt
flask_jsonrpc/contrib/browse/static/site.webmanifest
flask_jsonrpc/contrib/browse/static/css/bootstrap-browse.css
flask_jsonrpc/contrib/browse/static/css/bootstrap-theme.css
flask_jsonrpc/contrib/browse/static/css/bootstrap-theme.min.css
flask_jsonrpc/contrib/browse/static/css/bootstrap.min.css
flask_jsonrpc/contrib/browse/static/css/codemirror.min.css
flask_jsonrpc/contrib/browse/static/css/font-awesome-ie7.css
flask_jsonrpc/contrib/browse/static/css/font-awesome.css
flask_jsonrpc/contrib/browse/static/css/fonts.css
flask_jsonrpc/contrib/browse/static/css/loading-bar.min.css
flask_jsonrpc/contrib/browse/static/css/prettify.css
flask_jsonrpc/contrib/browse/static/fonts/FontAwesome.otf
flask_jsonrpc/contrib/browse/static/fonts/fontawesome-webfont.eot
flask_jsonrpc/contrib/browse/static/fonts/fontawesome-webfont.svg
flask_jsonrpc/contrib/browse/static/fonts/fontawesome-webfont.ttf
flask_jsonrpc/contrib/browse/static/fonts/fontawesome-webfont.woff
flask_jsonrpc/contrib/browse/static/fonts/glyphicons-halflings-regular.eot
flask_jsonrpc-4.0.0.dist-info/METADATA
flask_jsonrpc-4.0.0.dist-info/WHEEL
flask_jsonrpc-4.0.0.dist-info/licenses/LICENSE.txt
flask_jsonrpc-4.0.0.dist-info/RECORD
