Metadata-Version: 2.4
Name: Flask-JSONRPC
Version: 4.0.0
Summary: Adds JSONRPC support to Flask.
Author-email: Nycholas Oliveira <nycholas@cenobit.es>
Maintainer-email: "Cenobit Technologies Inc." <hi@cenobit.es>
License: Copyright (c) 2012-2024, Cenobit Technologies, Inc. http://cenobit.es/
Project-URL: Donate, https://github.com/sponsors/nycholas
Project-URL: Documentation, https://flask-jsonrpc.readthedocs.io/
Project-URL: Source Code, https://github.com/cenobites/flask-jsonrpc
Project-URL: Issue Tracker, https://github.com/cenobites/flask-jsonrpc/issues/
Project-URL: Website, https://flask-jsonrpc.readthedocs.io/
Keywords: flask,flask-extensions,jsonrpc
Classifier: Development Status :: 5 - Production/Stable
Classifier: Environment :: Web Environment
Classifier: Intended Audience :: Developers
Classifier: License :: OSI Approved :: BSD License
Classifier: Operating System :: OS Independent
Classifier: Programming Language :: Python
Classifier: Programming Language :: Python :: 3
Classifier: Programming Language :: Python :: 3 :: Only
Classifier: Programming Language :: Python :: 3.10
Classifier: Programming Language :: Python :: 3.11
Classifier: Programming Language :: Python :: 3.12
Classifier: Programming Language :: Python :: 3.13
Classifier: Programming Language :: Python :: 3.14
Classifier: Programming Language :: Python :: Free Threading :: 1 - Unstable
Classifier: Topic :: Internet :: WWW/HTTP :: Dynamic Content
Classifier: Topic :: Software Development :: Libraries :: Application Frameworks
Requires: mypy
Requires: pydantic
Requires-Python: >=3.10
License-File: LICENSE.txt
Requires-Dist: Flask<4.0,>=3.0.0
Requires-Dist: typeguard==4.4.4
Requires-Dist: typing-extensions>=4.3.0
Requires-Dist: typing-inspect==0.9.0
Requires-Dist: pydantic!=1.8,!=1.8.1,!=2.0.0,!=2.0.1,!=2.1.0,<3.0.0,>=1.7.4
Requires-Dist: eval-type-backport==0.3.1
Requires-Dist: annotated-types==0.7.0
Provides-Extra: async
Requires-Dist: Flask[async]<4.0,>=3.0.0; extra == "async"
Provides-Extra: dotenv
Requires-Dist: Flask[dotenv]<4.0,>=3.0.0; extra == "dotenv"
Dynamic: license-file
Dynamic: requires
